assistant_stream_ce/__init__.py
assistant_stream_ce/assistant_stream_chunk.py
assistant_stream_ce/assistant_stream_models.py
assistant_stream_ce/create_run.py
assistant_stream_ce/state_manager.py
assistant_stream_ce/state_proxy.py
assistant_stream_ce/modules/langgraph.py
assistant_stream_ce/modules/langgraph_chunk_merge.py
assistant_stream_ce/modules/tool_call.py
assistant_stream_ce/serialization/__init__.py
assistant_stream_ce/serialization/assistant_stream_response.py
assistant_stream_ce/serialization/assistant_transport.py
assistant_stream_ce/serialization/data_stream.py
assistant_stream_ce/serialization/openai_stream.py
assistant_stream_ce/serialization/stream_encoder.py
assistant_stream_ce-0.0.2.dist-info/METADATA
assistant_stream_ce-0.0.2.dist-info/WHEEL
assistant_stream_ce-0.0.2.dist-info/RECORD
