Metadata-Version: 2.4
Name: assistant-stream-ce
Version: 0.0.2
Summary: A documented version of the assistant-stream library, taken from the assistant-ui monorepo. 
Project-URL: Homepage, https://github.com/mylonasc/assistant-stream-ce
Project-URL: Issues, https://github.com/mylonasc/assistant-stream-ce/issues
Author-email: Charilaos Mylonas <mylonas.charilaos@gmail.com>
Classifier: License :: OSI Approved :: MIT License
Classifier: Operating System :: OS Independent
Classifier: Programming Language :: Python :: 3
Requires-Python: <4.0,>=3.11
Requires-Dist: asyncio>=4.0.0
Requires-Dist: fastapi>=0.125.0
Requires-Dist: langchain-openai>=1.1.6
Requires-Dist: langchain>=1.2.0
Requires-Dist: starlette>=0.37.2
Requires-Dist: uvicorn>=0.38.0
Provides-Extra: dev
Requires-Dist: pytest<8; extra == 'dev'
Provides-Extra: langgraph
Requires-Dist: langchain-core>=0.3.0; extra == 'langgraph'
